MANIFEST.in
README.rst
setup.py
docs/HISTORY.txt
docs/INSTALL.txt
docs/LICENSE.GPL
docs/LICENSE.txt
docs/TODO.txt
unice/.DS_Store
unice/__init__.py
unice.portlet.flickr.egg-info/PKG-INFO
unice.portlet.flickr.egg-info/SOURCES.txt
unice.portlet.flickr.egg-info/dependency_links.txt
unice.portlet.flickr.egg-info/entry_points.txt
unice.portlet.flickr.egg-info/namespace_packages.txt
unice.portlet.flickr.egg-info/not-zip-safe
unice.portlet.flickr.egg-info/requires.txt
unice.portlet.flickr.egg-info/top_level.txt
unice/portlet/.DS_Store
unice/portlet/__init__.py
unice/portlet/flickr/.DS_Store
unice/portlet/flickr/__init__.py
unice/portlet/flickr/configure.zcml
unice/portlet/flickr/flickrportlet.pt
unice/portlet/flickr/flickrportlet.py
unice/portlet/flickr/vocabularies.py
unice/portlet/flickr/browser/.DS_Store
unice/portlet/flickr/browser/__init__.py
unice/portlet/flickr/browser/configure.zcml
unice/portlet/flickr/browser/javascripts/scripts.js
unice/portlet/flickr/browser/stylesheets/styles.css
unice/portlet/flickr/profiles/.DS_Store
unice/portlet/flickr/profiles/default/cssregistry.xml
unice/portlet/flickr/profiles/default/jsregistry.xml
unice/portlet/flickr/profiles/default/metadata.xml
unice/portlet/flickr/profiles/default/portlets.xml
unice/portlet/flickr/tests/__init__.py
unice/portlet/flickr/tests/base.py
unice/portlet/flickr/tests/test_portlet.py